{
  "version": 1,
  "serviceConfiguration": {
    "apiName": "amplifyremixtodo",
    "serviceName": "AppSync",
    "gqlSchemaPath": "/tmp/amplify-6433a595-8630-4973-8f15-240154f1fed8/amplify/backend/api/amplifyremixtodo/schema.graphql",
    "defaultAuthType": {
      "mode": "API_KEY",
      "keyDescription": "api key description",
      "expirationTime": 30
    },
    "additionalAuthTypes": [
      {
        "mode": "AWS_IAM"
      }
    ],
    "conflictResolution": {
      "defaultResolutionStrategy": {
        "type": "AUTOMERGE"
      }
    }
  }
}